[{
  "voucher_id": 0,
  "image": "static/images/voucher/vouchertest1.png",
  "activated": false,
  "expiryDate": "2023-12-31T00:00:00.000",
  "priceDeduct": 5,
  "priceDiscount": 1
},
{
  "voucher_id": 1,
  "image": "static/images/voucher/vouchertest2.png",
  "activated": false,
  "expiryDate": "2025-06-14T00:00:00.000",
  "priceDeduct": 0,
  "priceDiscount": 0.85
},
{
  "voucher_id": 2,
  "image": "static/images/voucher/vouchertest3.png",
  "activated": false,
  "expiryDate": "2023-02-15T00:00:00.000",
  "priceDeduct": 0,
  "priceDiscount": 0.5
},
{
  "voucher_id": 3,
  "image": "static/images/voucher/vouchertest4.png",
  "activated": false,
  "expiryDate": "2023-05-30T00:00:00.000",
  "priceDeduct": 0,
  "priceDiscount": 0.9
},
{
  "voucher_id": 4,
  "image": "static/images/voucher/vouchertest5.png",
  "activated": false,
  "expiryDate": "2023-09-05T00:00:00.000",
  "priceDeduct": 2,
  "priceDiscount": 1
}]